sequence/__init__.py
sequence/message.py
sequence/protocol.py
sequence/app/__init__.py
sequence/app/random_request.py
sequence/components/__init__.py
sequence/components/beam_splitter.py
sequence/components/bsm.py
sequence/components/detector.py
sequence/components/interferometer.py
sequence/components/light_source.py
sequence/components/memory.py
sequence/components/optical_channel.py
sequence/components/photon.py
sequence/components/spdc_lens.py
sequence/components/switch.py
sequence/entanglement_management/__init__.py
sequence/entanglement_management/entanglement_protocol.py
sequence/entanglement_management/generation.py
sequence/entanglement_management/purification.py
sequence/entanglement_management/swapping.py
sequence/kernel/__init__.py
sequence/kernel/entity.py
sequence/kernel/event.py
sequence/kernel/eventlist.py
sequence/kernel/process.py
sequence/kernel/timeline.py
sequence/network_management/__init__.py
sequence/network_management/network_manager.py
sequence/network_management/reservation.py
sequence/network_management/routing.py
sequence/qkd/BB84.py
sequence/qkd/__init__.py
sequence/qkd/cascade.py
sequence/resource_management/__init__.py
sequence/resource_management/memory_manager.py
sequence/resource_management/resource_manager.py
sequence/resource_management/rule_manager.py
sequence/topology/__init__.py
sequence/topology/node.py
sequence/topology/topology.py
sequence/utils/__init__.py
sequence/utils/encoding.py
sequence/utils/log.py
sequence/utils/quantum_state.py
sequence_toolbox-0.2.2.dist-info/LICENSE
sequence_toolbox-0.2.2.dist-info/METADATA
sequence_toolbox-0.2.2.dist-info/WHEEL
sequence_toolbox-0.2.2.dist-info/top_level.txt
sequence_toolbox-0.2.2.dist-info/RECORD
