Metadata-Version: 2.1
Name: sequence-toolbox
Version: 0.2.2
Summary: Simulator of Quantum Network Communication: SEQUENCE-Python is a prototype version of the official SEQUENCE release.
Home-page: UNKNOWN
Author: Xiaoliang Wu, Joaquin Chung, Alexander Kolar, Eugene Wang, Tian Zhong, Rajkumar Kettimuthu, Martin Suchara
Author-email: xwu64@hawk.iit.edu, chungmiranda@anl.gov, akolar@anl.gov, eugenewang@yahoo.com, tzh@uchicago.edu, kettimut@mcs.anl.gov, msuchara@anl.gov
License: UNKNOWN
Platform: UNKNOWN
Requires-Dist: numpy
Requires-Dist: json5
Requires-Dist: pandas
